Metadata-Version: 1.0
Name: FormalSystems
Version: 0.1.3
Summary: Play with formal systems from "Gödel Escher Bach", Douglas Hofstadter
Home-page: http://alexprengere.github.com/FormalSystems
Author: Alex Prengère
Author-email: alexprengere@gmail.com
License: Apache License
